addcopyfighandler.py
addcopyfighandler-3.2.4.dist-info/WHEEL
addcopyfighandler-3.2.4.dist-info/METADATA
addcopyfighandler-3.2.4.dist-info/RECORD
