Metadata-Version: 2.1
Name: addcopyfighandler
Version: 3.2.4
Summary: Adds a Ctrl+C handler to matplotlib figures for copying the figure to the clipboard
Keywords: addcopyfighandler,figure,matplotlib,handler,copy
Author-email: Josh Burnett <github@burnettsonline.org>
Classifier: Development Status :: 5 - Production/Stable
Classifier: Intended Audience :: Developers
Classifier: License :: OSI Approved :: MIT License
Classifier: Programming Language :: Python
Classifier: Programming Language :: Python :: 3
Classifier: Programming Language :: Python :: 3.7
Classifier: Programming Language :: Python :: 3.8
Classifier: Programming Language :: Python :: 3.9
Classifier: Programming Language :: Python :: 3.10
Classifier: Programming Language :: Python :: 3.11
Classifier: Programming Language :: Python :: 3.12
Requires-Dist: matplotlib
Requires-Dist: pywin32;platform_system=='Windows'
Project-URL: Repository, https://github.com/joshburnett/addcopyfighandler
